wq/app/__init__.py
wq/app/static/app/.sha256
wq/app/static/app/css/.gitignore
wq/app/static/app/css/mapbox-gl-draw.css
wq/app/static/app/css/maplibre-gl.css
wq/app/static/app/css/wq.css
wq/app/static/app/js/.gitignore
wq/app/static/app/js/maplibre-gl.js
wq/app/static/app/js/maplibre-gl.js.map
wq/app/static/app/js/wq.dev.js
wq/app/static/app/js/wq.dev.js.map
wq/app/static/app/js/wq.js
wq/app/static/app/js/wq.js.map
wq.app-2.1.0.dist-info/LICENSE
wq.app-2.1.0.dist-info/LICENSES.md
wq.app-2.1.0.dist-info/METADATA
wq.app-2.1.0.dist-info/WHEEL
wq.app-2.1.0.dist-info/entry_points.txt
wq.app-2.1.0.dist-info/top_level.txt
wq.app-2.1.0.dist-info/RECORD
