Metadata-Version: 2.1
Name: wq.app
Version: 2.1.0
Summary: Offline-capable web/native apps for mobile surveys and field data collection.
Author-email: "S. Andrew Sheppard" <andrew@wq.io>
License: MIT
Project-URL: Homepage, https://wq.io/wq.app/
Project-URL: Documentation, https://wq.io/
Project-URL: Source, https://github.com/wq/wq.app
Project-URL: Release Notes, https://github.com/wq/wq.app/releases
Project-URL: Issues, https://github.com/wq/wq.app/issues
Project-URL: Tests, https://github.com/wq/wq.app/actions/workflows/test.yml
Classifier: Development Status :: 5 - Production/Stable
Classifier: Environment :: Web Environment
Classifier: License :: OSI Approved :: MIT License
Classifier: Natural Language :: English
Classifier: Programming Language :: JavaScript
Classifier: Programming Language :: Python :: 3
Classifier: Programming Language :: Python :: 3.7
Classifier: Programming Language :: Python :: 3.8
Classifier: Programming Language :: Python :: 3.9
Classifier: Programming Language :: Python :: 3.10
Classifier: Programming Language :: Python :: 3.11
Classifier: Framework :: Django
Classifier: Framework :: Django :: 3.2
Classifier: Framework :: Django :: 4.0
Classifier: Framework :: Django :: 4.1
Classifier: Framework :: Django :: 4.2
Classifier: Topic :: Software Development :: Libraries :: Application Frameworks
Classifier: Topic :: Text Processing :: Markup :: HTML
Classifier: Topic :: Scientific/Engineering :: GIS
Classifier: Topic :: Software Development :: Build Tools
Classifier: Topic :: Software Development :: Pre-processors
Requires-Python: >=3.7
License-File: LICENSE
License-File: LICENSES.md
Requires-Dist: wq.build
